probe_nrto/__init__.py
probe_nrto/analysis_tools/__init__.py
probe_nrto/analysis_tools/tf_model_interface.py
probe_nrto/analysis_tools/visual_utilities.py
probe_nrto/analysis_tools/visualization.py
probe_nrto/neural_structural_opt/__init__.py
probe_nrto/neural_structural_opt/autograd_lib.py
probe_nrto/neural_structural_opt/caching.py
probe_nrto/neural_structural_opt/models.py
probe_nrto/neural_structural_opt/pipeline_utils.py
probe_nrto/neural_structural_opt/problems.py
probe_nrto/neural_structural_opt/topo_api.py
probe_nrto/neural_structural_opt/topo_physics.py
probe_nrto/neural_structural_opt/train.py
neural_opt_surya-1.0.1.dist-info/METADATA
neural_opt_surya-1.0.1.dist-info/WHEEL
neural_opt_surya-1.0.1.dist-info/top_level.txt
neural_opt_surya-1.0.1.dist-info/RECORD
