Metadata-Version: 2.1
Name: neural_opt_surya
Version: 1.0.1
Summary: My package short description
Home-page: https://github.com/me/packaging_tutorial
Author: Surya
Author-email: my_email@email.address
License: MIT License
Keywords: keyword_1,keyword_2
Classifier: Development Status :: 4 - Beta
Classifier: Environment :: Console
Classifier: Intended Audience :: Science/Research
Classifier: Topic :: Scientific/Engineering
Classifier: Topic :: Scientific/Engineering :: Artificial Intelligence
Classifier: Topic :: Scientific/Engineering :: Physics
Classifier: License :: OSI Approved :: MIT License
Classifier: Natural Language :: English
Classifier: Programming Language :: Python :: 3
Requires-Python: >=3.6
